LICENSE
MANIFEST.in
README.rst
setup.cfg
setup.py
src/django_honeywords.egg-info/PKG-INFO
src/django_honeywords.egg-info/SOURCES.txt
src/django_honeywords.egg-info/dependency_links.txt
src/django_honeywords.egg-info/requires.txt
src/django_honeywords.egg-info/top_level.txt
src/honeywords/__init__.py
src/honeywords/admin.py
src/honeywords/apps.py
src/honeywords/backends.py
src/honeywords/hashers.py
src/honeywords/honeychecker.py
src/honeywords/honeywordgen.py
src/honeywords/models.py
src/honeywords/migrations/__init__.py
src/honeywords/tests/__init__.py
src/honeywords/tests/apps.py
src/honeywords/tests/test_TODO.py