Metadata-Version: 1.1
Name: django-honeywords
Version: 0.1.0b1
Summary: Django implementation of the Honeywords Project
Home-page: https://github.com/ooknosi/django_honeywords
Author: Edison KOO
Author-email: UNKNOWN
License: Apache Software License
Download-URL: https://github.com/ooknosi/django_honeywords/archive/0.1.0b1.tar.gz
Keywords: django honeywords password login security
Platform: UNKNOWN
Classifier: Development Status :: 4 - Beta
Classifier: Environment :: Web Environment
Classifier: Framework :: Django
Classifier: Framework :: Django :: 2.2
Classifier: Intended Audience :: Developers
Classifier: License :: OSI Approved :: Apache Software License
Classifier: Operating System :: OS Independent
Classifier: Programming Language :: Python
Classifier: Programming Language :: Python :: 3
Classifier: Programming Language :: Python :: 3.6
Classifier: Topic :: Internet :: WWW/HTTP
Classifier: Topic :: Internet :: WWW/HTTP :: Dynamic Content
Classifier: Topic :: Software Development :: Libraries :: Python Modules
